<samlp:AuthnRequest
    	xmlns:samlp="urn:oasis:names:tc:SAML:2.0:protocol"
    	xmlns:saml="urn:oasis:names:tc:SAML:2.0:assertion"
    	ID=""
    	Version="2.0"
    	IssueInstant=""
    	AssertionConsumerServiceIndex="0"
    	AttributeConsumingServiceIndex="0">
    	<saml:Issuer></saml:Issuer>
    	<samlp:NameIDPolicy
      	AllowCreate="true"
      	Format="urn:oasis:names:tc:SAML:2.0:nameid-format:transient"/>
	<Signature xmlns="http://www.w3.org/2000/09/xmldsig#">
<SignedInfo>
<CanonicalizationMethod Algorithm="http://www.w3.org/2001/10/xml-exc-c14n#"/>
<SignatureMethod Algorithm="http://www.w3.org/2000/09/xmldsig#rsa-sha1"/>
<Reference>
<Transforms>
<Transform Algorithm="http://www.w3.org/2000/09/xmldsig#enveloped-signature"/>
</Transforms>
<DigestMethod Algorithm="http://www.w3.org/2000/09/xmldsig#sha1"/>
<DigestValue/>
</Reference>
</SignedInfo>
<SignatureValue/>
<KeyInfo>
<KeyName/>
</KeyInfo>
</Signature>
  	</samlp:AuthnRequest>
